netschoolapi/__init__.py
netschoolapi/async_client_wrapper.py
netschoolapi/errors.py
netschoolapi/netschoolapi.py
netschoolapi/schemas.py
netschoolapi-11.0.4.dist-info/LICENSE
netschoolapi-11.0.4.dist-info/METADATA
netschoolapi-11.0.4.dist-info/WHEEL
netschoolapi-11.0.4.dist-info/top_level.txt
netschoolapi-11.0.4.dist-info/RECORD
