Metadata-Version: 2.1
Name: netschoolapi
Version: 11.0.4
Summary: Асинхронный API-клиент для «Сетевого города»
Home-page: https://github.com/nm17/netschoolapi/
Author: nm17
Author-email: dannevergame@gmail.com
Maintainer: igorlanov
Maintainer-email: vonalrogi@ya.ru
License: MIT
Classifier: License :: OSI Approved :: MIT License
Classifier: Natural Language :: Russian
Classifier: Topic :: Communications :: Chat
Classifier: Topic :: Education
Requires-Python: >=3.7
License-File: LICENSE
Requires-Dist: httpx (==0.23.3)
Requires-Dist: marshmallow (==3.19.0)
Requires-Dist: marshmallow-dataclass (==8.5.11)
Requires-Dist: typing-extensions (==4.4.0)
